agentis/__init__.py
agentis/agent/__init__.py
agentis/constants/__init__.py
agentis/langchain/__init__.py
agentis/tools/__init__.py
agentis/tools/burn_and_close_account.py
agentis/tools/create_gibwork.py
agentis/tools/create_image.py
agentis/tools/create_meteora_dlmm_pool.py
agentis/tools/deploy_token.py
agentis/tools/fetch_price.py
agentis/tools/get_balance.py
agentis/tools/get_token_data.py
agentis/tools/get_tps.py
agentis/tools/launch_pumpfun_token.py
agentis/tools/lend.py
agentis/tools/request_faucet_funds.py
agentis/tools/stake_with_jup.py
agentis/tools/trade.py
agentis/tools/transfer.py
agentis/tools/use_raydium.py
agentis/types/__init__.py
agentis/utils/__init__.py
agentis/utils/keypair.py
agentis/utils/meteora_dlmm/__init__.py
agentis/utils/meteora_dlmm/constants.py
agentis/utils/meteora_dlmm/helpers.py
agentis/utils/meteora_dlmm/idl.py
agentis/utils/meteora_dlmm/types.py
agentis/utils/meteora_dlmm/utils.py
agentis/utils/raydium/__init__.py
agentis/utils/raydium/constants.py
agentis/utils/raydium/layouts.py
agentis/utils/raydium/types.py
agentis/utils/raydium/utils.py
agentis/utils/send_tx.py
agentis/utils/toJSON.py
agentis-1.2.7.dist-info/LICENSE.md
agentis-1.2.7.dist-info/METADATA
agentis-1.2.7.dist-info/WHEEL
agentis-1.2.7.dist-info/RECORD
